img_processor/__init__.py
img_processor/cli.py
img_processor/img_processor.py
img_processor-0.20.0.dist-info/AUTHORS.rst
img_processor-0.20.0.dist-info/LICENSE
img_processor-0.20.0.dist-info/METADATA
img_processor-0.20.0.dist-info/WHEEL
img_processor-0.20.0.dist-info/entry_points.txt
img_processor-0.20.0.dist-info/top_level.txt
img_processor-0.20.0.dist-info/RECORD
