Metadata-Version: 2.1
Name: img-processor
Version: 0.20.0
Summary: Python package for taking an image and doing a thing
Home-page: https://github.com/kellerjustin/img_processor
Author: Justin Keller
Author-email: kellerjustin@protonmail.com
License: MIT license
Keywords: img_processor
Classifier: Development Status :: 2 - Pre-Alpha
Classifier: Intended Audience :: Developers
Classifier: License :: OSI Approved :: MIT License
Classifier: Natural Language :: English
Classifier: Programming Language :: Python :: 3
Classifier: Programming Language :: Python :: 3.6
Classifier: Programming Language :: Python :: 3.7
Classifier: Programming Language :: Python :: 3.8
Classifier: Programming Language :: Python :: 3.9
Classifier: Programming Language :: Python :: 3.10
Classifier: Programming Language :: Python :: 3.11
Requires-Python: >=3.6
License-File: LICENSE
License-File: AUTHORS.rst
Requires-Dist: numpy (>=1.24.3)
Requires-Dist: Click (>=8.1.3)
Requires-Dist: Pillow (>=9.5.0)
Requires-Dist: pytesseract (>=0.3.10)
Requires-Dist: pdf2image (>=1.16.3)
Requires-Dist: pypdf (>=3.10.0)
Requires-Dist: reportlab (>=4.0.4)
